{
  "_fv": 18,
  "_type": "armor",
  "definition": {
    "enableHelmet": true,
    "textureHelmet": "amber_helmet",
    "enableBody": true,
    "textureBody": "amber_chestplate",
    "enableLeggings": true,
    "textureLeggings": "amber_leggings_2",
    "enableBoots": true,
    "textureBoots": "amber_boots_2",
    "creativeTab": {
      "value": "CUSTOM:ToolsAndWeapons"
    },
    "armorTextureFile": "amber_",
    "helmetName": "Amber Helmet",
    "bodyName": "Amber Chestplate",
    "leggingsName": "Amber Leggings",
    "bootsName": "Amber Boots",
    "helmetSpecialInfo": [],
    "bodySpecialInfo": [],
    "leggingsSpecialInfo": [],
    "bootsSpecialInfo": [],
    "helmetModelName": "Default",
    "helmetModelPart": "Helmet",
    "helmetModelTexture": "From armor",
    "bodyModelName": "Default",
    "bodyModelPart": "Body",
    "bodyModelTexture": "From armor",
    "leggingsModelName": "Default",
    "leggingsModelPartL": "Leggings L",
    "leggingsModelPartR": "Leggings R",
    "leggingsModelTexture": "From armor",
    "bootsModelName": "Default",
    "bootsModelPartL": "Boots L",
    "bootsModelPartR": "Boots R",
    "bootsModelTexture": "From armor",
    "maxDamage": 75,
    "damageValueHelmet": 10,
    "damageValueBody": 20,
    "damageValueLeggings": 25,
    "damageValueBoots": 10,
    "enchantability": 45,
    "toughness": 1.5,
    "knockbackResistance": 0.0,
    "equipSound": {
      "value": ""
    },
    "repairItems": []
  }
}