{
  "group": "sotm",
  "type": "minecraft:crafting_shaped",
  "pattern": [
    "0  ",
    "34 ",
    "678"
  ],
  "key": {
    "0": {
      "item": "sotm:chorus_stone_bricks"
    },
    "3": {
      "item": "sotm:chorus_stone_bricks"
    },
    "4": {
      "item": "sotm:chorus_stone_bricks"
    },
    "6": {
      "item": "sotm:chorus_stone_bricks"
    },
    "7": {
      "item": "sotm:chorus_stone_bricks"
    },
    "8": {
      "item": "sotm:chorus_stone_bricks"
    }
  },
  "result": {
    "item": "sotm:chorus_stone_brick_stairs",
    "count": 6
  }
}